akmain/__init__.py
akmain-0.1.0.dist-info/licenses/LICENSE
akmain-0.1.0.dist-info/METADATA
akmain-0.1.0.dist-info/WHEEL
akmain-0.1.0.dist-info/top_level.txt
akmain-0.1.0.dist-info/RECORD
