Metadata-Version: 2.4
Name: akmain
Version: 0.1.0
Summary: A Python package by Aarush Kukreja for main processing tasks
Author-email: Aarush Kukreja <aarush@example.com>
Classifier: Development Status :: 3 - Alpha
Classifier: License :: OSI Approved :: MIT License
Classifier: Programming Language :: Python :: 3
Requires-Python: >=3.8
License-File: LICENSE
Dynamic: license-file
